burpy/__init__.py
burpy/command_line.py
burpy-0.1.dist-info/METADATA
burpy-0.1.dist-info/WHEEL
burpy-0.1.dist-info/entry_points.txt
burpy-0.1.dist-info/top_level.txt
burpy-0.1.dist-info/RECORD
