Metadata-Version: 2.1
Name: burpy
Version: 0.1
Summary: Burp HTTP history parser
Home-page: http://github.com/MatJosephs/burpy
Author: Matei Josephs
Author-email: majosephs@protonmail.com
License: MIT
Keywords: Burp Suite HTTP history parse
Requires-Dist: requests
Requires-Dist: bs4
Requires-Dist: pandas
